AUTHORS.rst
CONTRIBUTING.rst
HISTORY.rst
LICENSE
MANIFEST.in
README.rst
setup.cfg
setup.py
cosmoscope/__init__.py
cosmoscope/cli.py
cosmoscope/cosmoscope.py
cosmoscope.egg-info/PKG-INFO
cosmoscope.egg-info/SOURCES.txt
cosmoscope.egg-info/dependency_links.txt
cosmoscope.egg-info/entry_points.txt
cosmoscope.egg-info/not-zip-safe
cosmoscope.egg-info/requires.txt
cosmoscope.egg-info/top_level.txt
docs/Makefile
docs/authors.rst
docs/conf.py
docs/contributing.rst
docs/history.rst
docs/index.rst
docs/installation.rst
docs/make.bat
docs/readme.rst
docs/usage.rst
tests/test_cosmoscope.py