Metadata-Version: 1.1
Name: cosmoscope
Version: 0.1.0
Summary: Back-end server to handle astronomical operations and pass information to connected clients
Home-page: https://github.com/nmearl/cosmoscope
Author: Nicholas Earl
Author-email: contact@nicholasearl.me
License: MIT license
Keywords: cosmoscope
Platform: UNKNOWN
Classifier: Development Status :: 2 - Pre-Alpha
Classifier: Intended Audience :: Developers
Classifier: License :: OSI Approved :: MIT License
Classifier: Natural Language :: English
Classifier: Programming Language :: Python :: 2
Classifier: Programming Language :: Python :: 2.7
Classifier: Programming Language :: Python :: 3
Classifier: Programming Language :: Python :: 3.4
Classifier: Programming Language :: Python :: 3.5
Classifier: Programming Language :: Python :: 3.6
